{
    "Version": "2012-10-17",
    "Statement": [
        {
            "Sid": "VisualEditor0",
            "Effect": "Allow",
            "Action": [
                "iam:GenerateCredentialReport",
                "s3:ListAccessPointsForObjectLambda",
                "iam:GetAccountPasswordPolicy",
                "s3:GetAccessPoint",
                "iam:GetServiceLastAccessedDetailsWithEntities",
                "iam:ListServerCertificates",
                "s3:PutStorageLensConfiguration",
                "iam:GetServiceLastAccessedDetails",
                "iam:ListVirtualMFADevices",
                "iam:GetOrganizationsAccessReport",
                "iam:SetSecurityTokenServicePreferences",
                "iam:SimulateCustomPolicy",
                "iam:CreateAccountAlias",
                "iam:GetAccountAuthorizationDetails",
                "iam:DeleteAccountAlias",
                "iam:GetCredentialReport",
                "iam:ListPolicies",
                "iam:DeleteAccountPasswordPolicy",
                "s3:ListJobs",
                "iam:ListRoles",
                "s3:ListMultiRegionAccessPoints",
                "s3:ListStorageLensConfigurations",
                "iam:GetContextKeysForCustomPolicy",
                "s3:GetAccountPublicAccessBlock",
                "s3:ListAllMyBuckets",
                "iam:UpdateAccountPasswordPolicy",
                "iam:ListAccountAliases",
                "iam:ListUsers",
                "iam:ListGroups",
                "iam:GetAccountSummary"
            ],
            "Resource": "*"
        },
        {
            "Sid": "VisualEditor1",
            "Effect": "Allow",
            "Action": [
                "iam:CreateServiceSpecificCredential",
                "iam:DeactivateMFADevice",
                "iam:DeleteAccessKey",
                "iam:GenerateServiceLastAccessedDetails",
                "iam:UpdateOpenIDConnectProviderThumbprint",
                "iam:ListServiceSpecificCredentials",
                "iam:PutRolePolicy",
                "iam:ListSigningCertificates",
                "iam:AddRoleToInstanceProfile",
                "iam:DeleteServerCertificate",
                "iam:UploadSSHPublicKey",
                "iam:DetachGroupPolicy",
                "iam:DeleteOpenIDConnectProvider",
                "iam:PutGroupPolicy",
                "iam:UpdateServiceSpecificCredential",
                "iam:GetRole",
                "iam:GetPolicy",
                "iam:RemoveClientIDFromOpenIDConnectProvider",
                "iam:ListEntitiesForPolicy",
                "iam:DeleteRole",
                "iam:UpdateRoleDescription",
                "iam:UpdateServerCertificate",
                "iam:CreateInstanceProfile",
                "iam:PutRolePermissionsBoundary",
                "iam:ResetServiceSpecificCredential",
                "s3:ListBucket",
                "iam:DeleteRolePermissionsBoundary",
                "iam:GetServiceLinkedRoleDeletionStatus",
                "iam:DeleteRolePolicy",
                "iam:EnableMFADevice",
                "iam:ResyncMFADevice",
                "iam:ListAttachedGroupPolicies",
                "iam:UpdateSAMLProvider",
                "iam:ListAccessKeys",
                "iam:DeleteInstanceProfile",
                "iam:ListGroupPolicies",
                "iam:GetSSHPublicKey",
                "iam:PutUserPermissionsBoundary",
                "iam:DeleteUser",
                "iam:DeleteUserPermissionsBoundary",
                "iam:CreatePolicy",
                "iam:AttachGroupPolicy",
                "iam:DeleteVirtualMFADevice",
                "iam:PutUserPolicy",
                "iam:UpdateRole",
                "iam:GetUser",
                "iam:DeleteServiceSpecificCredential",
                "iam:GetLoginProfile",
                "iam:DeleteSAMLProvider",
                "iam:GetPolicyVersion",
                "iam:DeleteGroup",
                "iam:UpdateGroup",
                "iam:CreateRole",
                "iam:AttachRolePolicy",
                "iam:CreateLoginProfile",
                "iam:ListSSHPublicKeys",
                "iam:DetachRolePolicy",
                "iam:SimulatePrincipalPolicy",
                "iam:DetachUserPolicy",
                "iam:ChangePassword",
                "iam:UpdateLoginProfile",
                "iam:CreateGroup",
                "iam:UpdateUser",
                "iam:GetAccessKeyLastUsed",
                "iam:DeleteUserPolicy",
                "iam:AttachUserPolicy",
                "iam:UpdateAccessKey",
                "iam:UpdateSSHPublicKey",
                "iam:DeleteSigningCertificate",
                "iam:GetUserPolicy",
                "iam:ListGroupsForUser",
                "iam:DeleteServiceLinkedRole",
                "iam:GetGroupPolicy",
                "iam:DeleteSSHPublicKey",
                "iam:DeletePolicy",
                "iam:CreateSAMLProvider",
                "iam:CreateVirtualMFADevice",
                "iam:ListMFADevices",
                "iam:CreateUser",
                "iam:GetGroup",
                "iam:CreateAccessKey",
                "iam:GetContextKeysForPrincipalPolicy",
                "iam:AddUserToGroup",
                "iam:RemoveUserFromGroup",
                "iam:GenerateOrganizationsAccessReport",
                "iam:ListAttachedUserPolicies",
                "iam:CreatePolicyVersion",
                "iam:DeleteLoginProfile",
                "iam:UploadSigningCertificate",
                "iam:GetInstanceProfile",
                "iam:ListUserPolicies",
                "iam:ListInstanceProfiles",
                "iam:CreateOpenIDConnectProvider",
                "iam:UploadServerCertificate",
                "iam:UpdateSigningCertificate",
                "iam:DeleteGroupPolicy",
                "iam:DeletePolicyVersion",
                "iam:ListUserTags"
            ],
            "Resource": [
                "arn:aws:iam::352620587691:saml-provider/*",
                "arn:aws:iam::352620587691:oidc-provider/*",
                "arn:aws:iam::352620587691:access-report/*",
                "arn:aws:iam::352620587691:user/*",
                "arn:aws:iam::352620587691:mfa/*",
                "arn:aws:iam::352620587691:instance-profile/*",
                "arn:aws:iam::352620587691:sms-mfa/*",
                "arn:aws:iam::352620587691:server-certificate/*",
                "arn:aws:iam::352620587691:group/iampolicydev",
                "arn:aws:iam::352620587691:role/*",
                "arn:aws:iam::352620587691:policy/*",
                "arn:aws:s3:::rohitbucket11"
            ]
        },
        {
            "Sid": "VisualEditor2",
            "Effect": "Allow",
            "Action": [
                "s3:DeleteObjectVersion",
                "s3:GetObjectVersionTagging",
                "s3:RestoreObject",
                "s3:ReplicateObject",
                "s3:GetObjectVersionTorrent",
                "s3:GetObjectAcl",
                "s3:AbortMultipartUpload",
                "s3:GetObjectVersionAcl",
                "s3:GetObjectTagging",
                "s3:DeleteObject",
                "s3:CreateMultiRegionAccessPoint",
                "s3:GetMultiRegionAccessPointPolicyStatus",
                "s3:GetObjectRetention",
                "s3:GetMultiRegionAccessPointPolicy",
                "s3:GetMultiRegionAccessPoint",
                "s3:DeleteMultiRegionAccessPoint",
                "s3:PutObjectLegalHold",
                "s3:GetObjectLegalHold",
                "s3:ListMultipartUploadParts",
                "s3:PutObject",
                "s3:GetObject",
                "s3:GetObjectTorrent",
                "s3:PutObjectRetention",
                "s3:GetObjectVersionForReplication",
                "s3:ReplicateDelete",
                "s3:GetObjectVersion"
            ],
            "Resource": [
                "arn:aws:s3:::*/*",
                "arn:aws:s3::352620587691:accesspoint/*"
            ]
        },
        {
            "Sid": "VisualEditor3",
            "Effect": "Allow",
            "Action": [
                "s3:PutAccessPointConfigurationForObjectLambda",
                "s3:DeleteAccessPoint",
                "s3:CreateBucket",
                "s3:DeleteAccessPointForObjectLambda",
                "s3:GetStorageLensConfigurationTagging",
                "s3:GetBucketObjectLockConfiguration",
                "s3:DeleteBucketWebsite",
                "s3:GetIntelligentTieringConfiguration",
                "s3:PutLifecycleConfiguration",
                "s3:GetBucketPolicyStatus",
                "s3:GetBucketWebsite",
                "s3:GetJobTagging",
                "s3:GetBucketNotification",
                "s3:GetReplicationConfiguration",
                "s3:PutBucketNotification",
                "s3:DescribeJob",
                "s3:PutBucketLogging",
                "s3:GetAnalyticsConfiguration",
                "s3:PutBucketObjectLockConfiguration",
                "s3:GetAccessPointForObjectLambda",
                "s3:GetStorageLensDashboard",
                "s3:CreateAccessPoint",
                "s3:GetLifecycleConfiguration",
                "s3:GetInventoryConfiguration",
                "s3:GetBucketTagging",
                "s3:PutAccelerateConfiguration",
                "s3:GetAccessPointPolicyForObjectLambda",
                "s3:GetBucketLogging",
                "s3:ListBucket",
                "s3:GetAccelerateConfiguration",
                "s3:GetBucketPolicy",
                "s3:PutEncryptionConfiguration",
                "s3:GetEncryptionConfiguration",
                "s3:GetBucketRequestPayment",
                "s3:DeleteBucketOwnershipControls"
            ],
            "Resource": [
                "arn:aws:s3:::*",
                "arn:aws:s3:*:352620587691:accesspoint/*",
                "arn:aws:s3:*:352620587691:job/*",
                "arn:aws:s3-object-lambda:*:352620587691:accesspoint/*",
                "arn:aws:s3:*:352620587691:storage-lens/*",
                "arn:aws:s3:*:352620587691:storage-lens/*"
            ]
        }
    ]
}